[
  {
    "id": "LOCAL009",
    "grade": "1",
    "unit": "植物の体のつくりと分類",
    "keywords": "ルーペ,スケッチ,主根,側根,双子葉類,単子葉類,網状脈,平行脈,ゼニゴケ,胞子",
    "year": "2024",
    "month": "",
    "testType": "学力テスト",
    "comment": "",
    "pageCount": "1",
    "createdAt": "2026-01-16T12:02:01.591Z"
  },
  {
    "id": "LOCAL010",
    "grade": "1",
    "unit": "植物の分類",
    "keywords": "種子植物,被子植物,裸子植物,単子葉類,双子葉類,シダ植物,コケ植物,胞子,維管束,平行脈",
    "year": "2024",
    "month": "",
    "testType": "学力テスト",
    "comment": "",
    "pageCount": "1",
    "createdAt": "2026-01-16T12:03:04.984Z"
  },
  {
    "id": "LOCAL011",
    "grade": "1",
    "unit": "植物のからだのつくりと分類",
    "keywords": "ひげ根,主根,側根,単子葉類,双子葉類,葉脈,平行脈,網目状脈,根毛,表面積",
    "year": "2024",
    "month": "",
    "testType": "学力テスト",
    "comment": "",
    "pageCount": "1",
    "createdAt": "2026-01-16T12:03:35.968Z"
  },
  {
    "id": "LOCAL012",
    "grade": "1",
    "unit": "植物の分類",
    "keywords": "被子植物,裸子植物,双子葉類,単子葉類,胚珠,子房,シダ植物,コケ植物,胞子のう,維管束",
    "year": "2022",
    "month": "12",
    "testType": "学力テスト",
    "comment": "",
    "pageCount": "1",
    "createdAt": "2026-01-16T12:04:25.313Z"
  },
  {
    "id": "LOCAL013",
    "grade": "1",
    "unit": "植物の分類",
    "keywords": "シダ植物,コケ植物,裸子植物,被子植物,単子葉類,双子葉類,胚珠,胞子,維管束,種子植物",
    "year": "2022",
    "month": "7",
    "testType": "学力テスト",
    "comment": "",
    "pageCount": "1",
    "createdAt": "2026-01-16T12:05:05.325Z"
  },
  {
    "id": "LOCAL014",
    "grade": "2",
    "unit": "動物の分類",
    "keywords": "脊椎動物,無脊椎動物,胎生,卵生,軟体動物,節足動物,両生類,爬虫類,えら呼吸,肺呼吸",
    "year": "2022",
    "month": "",
    "testType": "学力テスト",
    "comment": "",
    "pageCount": "1",
    "createdAt": "2026-01-16T12:05:45.082Z"
  },
  {
    "id": "LOCAL015",
    "grade": "1",
    "unit": "植物の分類",
    "keywords": "種子植物,被子植物,裸子植物,双子葉類,単子葉類,シダ植物,コケ植物,子房,胚珠,維管束",
    "year": "2022",
    "month": "",
    "testType": "学力テスト",
    "comment": "",
    "pageCount": "1",
    "createdAt": "2026-01-16T12:06:43.289Z"
  },
  {
    "id": "LOCAL016",
    "grade": "1",
    "unit": "植物の分類",
    "keywords": "種子植物,被子植物,裸子植物,双子葉類,単子葉類,合弁花類,離弁花類,シダ植物,コケ植物,維管束",
    "year": "2022",
    "month": "",
    "testType": "学力テスト",
    "comment": "",
    "pageCount": "1",
    "createdAt": "2026-01-16T12:07:13.731Z"
  },
  {
    "id": "LOCAL017",
    "grade": "1",
    "unit": "植物の分類",
    "keywords": "種子植物,被子植物,裸子植物,単子葉類,双子葉類,胚珠,子房,合弁花,離弁花,胞子",
    "year": "2022",
    "month": "",
    "testType": "学力テスト",
    "comment": "",
    "pageCount": "1",
    "createdAt": "2026-01-16T12:07:45.967Z"
  },
  {
    "id": "LOCAL018",
    "grade": "1",
    "unit": "植物の分類",
    "keywords": "被子植物,裸子植物,単子葉類,双子葉類,シダ植物,コケ植物,維管束,ひげ根,主根・側根,合弁花",
    "year": "2022",
    "month": "",
    "testType": "学力テスト",
    "comment": "",
    "pageCount": "1",
    "createdAt": "2026-01-16T12:08:30.729Z"
  },
  {
    "id": "LOCAL019",
    "grade": "1",
    "unit": "動物の分類",
    "keywords": "脊椎動物,無脊椎動物,胎生,卵生,節足動物,軟体動物,外骨格,両生類,は虫類,昆虫類",
    "year": "2024",
    "month": "",
    "testType": "学力テスト",
    "comment": "",
    "pageCount": "1",
    "createdAt": "2026-01-16T12:12:44.788Z"
  }
]